keyring_proxy_stdio/__init__.py
keyring_proxy_stdio/_version.py
keyring_proxy_stdio-0.1.11.dist-info/METADATA
keyring_proxy_stdio-0.1.11.dist-info/WHEEL
keyring_proxy_stdio-0.1.11.dist-info/entry_points.txt
keyring_proxy_stdio-0.1.11.dist-info/RECORD
