Metadata-Version: 2.3
Name: keyring-proxy-stdio
Version: 0.1.11
Summary: Default template for PDM package
Author-email: "Kalle M. Aagaard" <git@k-moeller.dk>
License: MIT
Requires-Python: >=3.12
Requires-Dist: keyring-proxy>=0.2.15
